{
  "db": "PostgreSQL",
  "087ba44d7aab2674dfe0e3bebe34d6712495ce89ddeafefb6c96aae6dce41ceb": {
    "describe": {
      "columns": [],
      "nullable": [],
      "parameters": {
        "Left": [
          "Text",
          "Record"
        ]
      }
    },
    "query": "UPDATE users SET avatar = $1 WHERE id = $2"
  },
  "28dab3a902e30d7170e1502017801bd67027461b8a87b5f84b8c9f6e94a4747d": {
    "describe": {
      "columns": [
        {
          "name": "user_id: PostgresU128",
          "ordinal": 0,
          "type_info": {
            "Custom": {
              "kind": {
                "Composite": [
                  [
                    "high",
                    "Int8"
                  ],
                  [
                    "low",
                    "Int8"
                  ]
                ]
              },
              "name": "u128"
            }
          }
        }
      ],
      "nullable": [
        false
      ],
      "parameters": {
        "Left": [
          "Text"
        ]
      }
    },
    "query": "SELECT user_id AS \"user_id: PostgresU128\" FROM tokens WHERE token = $1"
  },
  "39f51300bab47dcf9f7f056d01a9f10953149bb31999b428eac952e40293cd81": {
    "describe": {
      "columns": [
        {
          "name": "username",
          "ordinal": 0,
          "type_info": "Text"
        },
        {
          "name": "discriminator",
          "ordinal": 1,
          "type_info": "Int2"
        },
        {
          "name": "email",
          "ordinal": 2,
          "type_info": "Text"
        },
        {
          "name": "avatar",
          "ordinal": 3,
          "type_info": "Text"
        },
        {
          "name": "banner",
          "ordinal": 4,
          "type_info": "Text"
        },
        {
          "name": "bio",
          "ordinal": 5,
          "type_info": "Text"
        },
        {
          "name": "flags",
          "ordinal": 6,
          "type_info": "Int4"
        }
      ],
      "nullable": [
        false,
        false,
        true,
        true,
        true,
        true,
        false
      ],
      "parameters": {
        "Left": [
          "Record"
        ]
      }
    },
    "query": "SELECT\n            username,\n            discriminator,\n            email,\n            avatar,\n            banner,\n            bio,\n            flags\n        FROM\n            users\n        WHERE\n            id = $1"
  },
  "3d7ebe93e552692fedc80e2c37f4ca0a0de12b835a6a47f1442609bd9291aa19": {
    "describe": {
      "columns": [
        {
          "name": "password",
          "ordinal": 0,
          "type_info": "Text"
        }
      ],
      "nullable": [
        true
      ],
      "parameters": {
        "Left": [
          "Record"
        ]
      }
    },
    "query": "SELECT password FROM users WHERE id = $1"
  },
  "45a536b46a3654b06157d263f6722d44ca054a529c6e7f80f94b17c7c557d31b": {
    "describe": {
      "columns": [
        {
          "name": "token",
          "ordinal": 0,
          "type_info": "Text"
        }
      ],
      "nullable": [
        false
      ],
      "parameters": {
        "Left": [
          "Record"
        ]
      }
    },
    "query": "SELECT token FROM tokens WHERE user_id = $1"
  },
  "47688f8505f4765df616015354ad8213801ad17970a82e3ba2195e3abc3d14df": {
    "describe": {
      "columns": [],
      "nullable": [],
      "parameters": {
        "Left": [
          {
            "Custom": {
              "kind": {
                "Composite": [
                  [
                    "high",
                    "Int8"
                  ],
                  [
                    "low",
                    "Int8"
                  ]
                ]
              },
              "name": "u128"
            }
          },
          {
            "Custom": {
              "kind": {
                "Composite": [
                  [
                    "high",
                    "Int8"
                  ],
                  [
                    "low",
                    "Int8"
                  ]
                ]
              },
              "name": "u128"
            }
          }
        ]
      }
    },
    "query": "INSERT INTO role_data (guild_id, role_id, user_id) VALUES ($1, $1, $2)"
  },
  "4c82c07c8672b5b1f1aa2a7c97164d20b194ecca58657322a6b3d5b055d00ade": {
    "describe": {
      "columns": [
        {
          "name": "discriminator",
          "ordinal": 0,
          "type_info": "Int2"
        }
      ],
      "nullable": [
        false
      ],
      "parameters": {
        "Left": [
          {
            "Custom": {
              "kind": {
                "Composite": [
                  [
                    "high",
                    "Int8"
                  ],
                  [
                    "low",
                    "Int8"
                  ]
                ]
              },
              "name": "u128"
            }
          },
          "Text",
          "Text",
          "Text"
        ]
      }
    },
    "query": "INSERT INTO\n            users (id, username, email, password)\n        VALUES\n            ($1, $2, $3, $4)\n        RETURNING\n            discriminator"
  },
  "50293c2e54af11d4c2a553e29b671cef087a159c6ee7182d8ca929ecb748f3b7": {
    "describe": {
      "columns": [],
      "nullable": [],
      "parameters": {
        "Left": [
          "Record"
        ]
      }
    },
    "query": "DELETE FROM users WHERE id = $1"
  },
  "52645061c871d222d342edf74fa669f5e853ec6b16202c334e1d09ca449df7c4": {
    "describe": {
      "columns": [
        {
          "name": "joined_at",
          "ordinal": 0,
          "type_info": "Timestamptz"
        }
      ],
      "nullable": [
        false
      ],
      "parameters": {
        "Left": [
          {
            "Custom": {
              "kind": {
                "Composite": [
                  [
                    "high",
                    "Int8"
                  ],
                  [
                    "low",
                    "Int8"
                  ]
                ]
              },
              "name": "u128"
            }
          },
          {
            "Custom": {
              "kind": {
                "Composite": [
                  [
                    "high",
                    "Int8"
                  ],
                  [
                    "low",
                    "Int8"
                  ]
                ]
              },
              "name": "u128"
            }
          }
        ]
      }
    },
    "query": "INSERT INTO members (id, guild_id) VALUES ($1, $2) RETURNING joined_at"
  },
  "5b40708e478432b21a80fb59ee822061d87c99e28e0a9e65d2e77ef49600a83b": {
    "describe": {
      "columns": [],
      "nullable": [],
      "parameters": {
        "Left": [
          "Text",
          "Record"
        ]
      }
    },
    "query": "UPDATE users SET bio = $1 WHERE id = $2"
  },
  "621648866e6e40f15f725c2b4d5012b927bd84b3cd351543851021d319d63e8f": {
    "describe": {
      "columns": [
        {
          "name": "username",
          "ordinal": 0,
          "type_info": "Text"
        },
        {
          "name": "discriminator",
          "ordinal": 1,
          "type_info": "Int2"
        },
        {
          "name": "avatar",
          "ordinal": 2,
          "type_info": "Text"
        },
        {
          "name": "banner",
          "ordinal": 3,
          "type_info": "Text"
        },
        {
          "name": "bio",
          "ordinal": 4,
          "type_info": "Text"
        },
        {
          "name": "flags",
          "ordinal": 5,
          "type_info": "Int4"
        }
      ],
      "nullable": [
        false,
        false,
        true,
        true,
        true,
        false
      ],
      "parameters": {
        "Left": [
          "Record"
        ]
      }
    },
    "query": "SELECT\n            username,\n            discriminator,\n            avatar,\n            banner,\n            bio,\n            flags\n        FROM\n            users\n        WHERE\n            id = $1"
  },
  "6ead10a4ea43d6e21372f6bd5092ef344faa928d3b2a3cfd73b0be1bbf75eac2": {
    "describe": {
      "columns": [
        {
          "name": "discriminator",
          "ordinal": 0,
          "type_info": "Int2"
        }
      ],
      "nullable": [
        false
      ],
      "parameters": {
        "Left": [
          "Text",
          "Int2"
        ]
      }
    },
    "query": "SELECT discriminator FROM users WHERE username = $1 AND discriminator = $2"
  },
  "7b4b5b818b40cb78c177f05e13b277ef76102c1214c6280073f3a7e8a94ba4ef": {
    "describe": {
      "columns": [
        {
          "name": "email",
          "ordinal": 0,
          "type_info": "Text"
        }
      ],
      "nullable": [
        true
      ],
      "parameters": {
        "Left": [
          "Text"
        ]
      }
    },
    "query": "SELECT email FROM users WHERE email = $1"
  },
  "7d3aa30c43c94db6578cdd47bd1d55460c1ffbcd7dda59a39b3ff783a2d8cc2d": {
    "describe": {
      "columns": [],
      "nullable": [],
      "parameters": {
        "Left": [
          {
            "Custom": {
              "kind": {
                "Composite": [
                  [
                    "high",
                    "Int8"
                  ],
                  [
                    "low",
                    "Int8"
                  ]
                ]
              },
              "name": "u128"
            }
          },
          "Text",
          "Text",
          "Text",
          "Text",
          {
            "Custom": {
              "kind": {
                "Composite": [
                  [
                    "high",
                    "Int8"
                  ],
                  [
                    "low",
                    "Int8"
                  ]
                ]
              },
              "name": "u128"
            }
          },
          "Int4"
        ]
      }
    },
    "query": "INSERT INTO\n            guilds (id, name, description, icon, banner, owner_id, flags)\n        VALUES\n            ($1, $2, $3, $4, $5, $6, $7)\n        "
  },
  "82656124ef41560bc2fe44a9e64c26c52399c0b3410f5eef6a609823a599e93d": {
    "describe": {
      "columns": [],
      "nullable": [],
      "parameters": {
        "Left": [
          "Record"
        ]
      }
    },
    "query": "DELETE FROM tokens WHERE user_id = $1"
  },
  "87742854ab3161409d6fb266f96c1d251b75dc157e95dbeb9b13b915b8fee9af": {
    "describe": {
      "columns": [
        {
          "name": "out",
          "ordinal": 0,
          "type_info": "Int2"
        }
      ],
      "nullable": [
        null
      ],
      "parameters": {
        "Left": [
          "Text"
        ]
      }
    },
    "query": "SELECT generate_discriminator($1) AS out"
  },
  "98343210dae5830ad351180ca43dd72e77876c52771e8718197e43da14028cb3": {
    "describe": {
      "columns": [],
      "nullable": [],
      "parameters": {
        "Left": [
          {
            "Custom": {
              "kind": {
                "Composite": [
                  [
                    "high",
                    "Int8"
                  ],
                  [
                    "low",
                    "Int8"
                  ]
                ]
              },
              "name": "u128"
            }
          },
          {
            "Custom": {
              "kind": {
                "Composite": [
                  [
                    "high",
                    "Int8"
                  ],
                  [
                    "low",
                    "Int8"
                  ]
                ]
              },
              "name": "u128"
            }
          }
        ]
      }
    },
    "query": "INSERT INTO channels VALUES (\n            $1, $2, 'text', 'general', 0, null, null, null, 0, false, false\n        )\n        "
  },
  "bbfc76e3af9ea14f7db905a60a55ee902e6fd91abc1637767c9d65cf54d16d01": {
    "describe": {
      "columns": [],
      "nullable": [],
      "parameters": {
        "Left": [
          {
            "Custom": {
              "kind": {
                "Composite": [
                  [
                    "high",
                    "Int8"
                  ],
                  [
                    "low",
                    "Int8"
                  ]
                ]
              },
              "name": "u128"
            }
          },
          "Text"
        ]
      }
    },
    "query": "INSERT INTO tokens (user_id, token) VALUES ($1, $2)"
  },
  "d4b505cd03d6f5475e74b5c82aa19ed275202a16bbf174586bd24db2ab03cf87": {
    "describe": {
      "columns": [
        {
          "name": "allowed_permissions",
          "ordinal": 0,
          "type_info": "Int8"
        },
        {
          "name": "denied_permissions",
          "ordinal": 1,
          "type_info": "Int8"
        }
      ],
      "nullable": [
        true,
        true
      ],
      "parameters": {
        "Left": [
          {
            "Custom": {
              "kind": {
                "Composite": [
                  [
                    "high",
                    "Int8"
                  ],
                  [
                    "low",
                    "Int8"
                  ]
                ]
              },
              "name": "u128"
            }
          },
          {
            "Custom": {
              "kind": {
                "Composite": [
                  [
                    "high",
                    "Int8"
                  ],
                  [
                    "low",
                    "Int8"
                  ]
                ]
              },
              "name": "u128"
            }
          },
          "Int4"
        ]
      }
    },
    "query": "INSERT INTO roles\n            (id, guild_id, name, flags)\n        VALUES\n            ($1, $2, 'Default', $3)\n        RETURNING\n            allowed_permissions, denied_permissions\n        "
  },
  "d6936366559a2ff31bf0d5346b9e01c226dd6da007bfe74c1ea9d05b82d60481": {
    "describe": {
      "columns": [],
      "nullable": [],
      "parameters": {
        "Left": [
          "Text",
          "Int2",
          "Record"
        ]
      }
    },
    "query": "UPDATE users SET username = $1, discriminator = $2 WHERE id = $3"
  },
  "e799fe200b7987bdceddf4e0db31fe441478e026aef3bc1be4a5f01fa6325026": {
    "describe": {
      "columns": [],
      "nullable": [],
      "parameters": {
        "Left": [
          "Text",
          "Record"
        ]
      }
    },
    "query": "UPDATE users SET banner = $1 WHERE id = $2"
  },
  "f4d518e1cd7bc7ae03e5d9e75b568fc0b2eac97cd3919ec27f5d75aa71ac14eb": {
    "describe": {
      "columns": [
        {
          "name": "id: PostgresU128",
          "ordinal": 0,
          "type_info": {
            "Custom": {
              "kind": {
                "Composite": [
                  [
                    "high",
                    "Int8"
                  ],
                  [
                    "low",
                    "Int8"
                  ]
                ]
              },
              "name": "u128"
            }
          }
        },
        {
          "name": "password",
          "ordinal": 1,
          "type_info": "Text"
        },
        {
          "name": "flags",
          "ordinal": 2,
          "type_info": "Int4"
        }
      ],
      "nullable": [
        false,
        true,
        false
      ],
      "parameters": {
        "Left": [
          "Text"
        ]
      }
    },
    "query": "SELECT id as \"id: PostgresU128\", password, flags FROM users WHERE email = $1"
  }
}